nostalgia/__init__.py
nostalgia/anonimizer.py
nostalgia/anonymizer.py
nostalgia/cache.py
nostalgia/data_loading.py
nostalgia/extracter.py
nostalgia/file_caching.py
nostalgia/ndf.py
nostalgia/nlp.py
nostalgia/selenium.py
nostalgia/times.py
nostalgia/unzip.py
nostalgia/utils.py
nostalgia/data/samples/chrome_history.parquet
nostalgia/data/samples/fitbit_heartrate.parquet
nostalgia/data/samples/google_gmail.parquet
nostalgia/data/samples/google_places.parquet
nostalgia/data/samples/ing_payments.parquet
nostalgia/data/samples/web_events.parquet
nostalgia/data/samples/web_google_search.parquet
nostalgia/data/samples/web_offers.parquet
nostalgia/data/samples/web_videos.parquet
nostalgia/data/samples/web_videos_watched.parquet
nostalgia/enrichers/google/.env.example
nostalgia/enrichers/google/custom_search.py
nostalgia/interfaces/__init__.py
nostalgia/interfaces/chat.py
nostalgia/interfaces/places.py
nostalgia/interfaces/post.py
nostalgia/sources/__init__.py
nostalgia/sources/abnamro.py
nostalgia/sources/albert_heijn.py
nostalgia/sources/chrome_history.parquet
nostalgia/sources/chrome_history.py
nostalgia/sources/emacs_file_visits.py
nostalgia/sources/email.py
nostalgia/sources/mijn_chipkaart.py
nostalgia/sources/ns_chipkaart.py
nostalgia/sources/reddit_posts.py
nostalgia/sources/screenshots.py
nostalgia/sources/shazam.py
nostalgia/sources/sleepcycle.py
nostalgia/sources/spotify.py
nostalgia/sources/whatsapp.py
nostalgia/sources/apple/__init__.py
nostalgia/sources/apple/icloud.py
nostalgia/sources/apple/storesactivity.py
nostalgia/sources/facebook/__init__.py
nostalgia/sources/facebook/messages.py
nostalgia/sources/facebook/posts.py
nostalgia/sources/fitbit/__init__.py
nostalgia/sources/fitbit/heartrate.parquet
nostalgia/sources/fitbit/heartrate.py
nostalgia/sources/fitbit/sleep.py
nostalgia/sources/google/README.md
nostalgia/sources/google/__init__.py
nostalgia/sources/google/app_usage.py
nostalgia/sources/google/calendar.py
nostalgia/sources/google/gmail.parquet
nostalgia-0.1.67.dist-info/METADATA
nostalgia-0.1.67.dist-info/WHEEL
nostalgia-0.1.67.dist-info/top_level.txt
nostalgia-0.1.67.dist-info/RECORD
