Metadata-Version: 2.1
Name: nostalgia
Version: 0.1.67
Summary: nostalgia enables to self-track and gain insights into your life
Home-page: https://github.com/nostalgia-dev/nostalgia
Author: Pascal van Kooten
Author-email: kootenpv@gmail.com
License: MIT
Platform: any
Classifier: Environment :: Console
Classifier: Intended Audience :: Developers
Classifier: Intended Audience :: Customer Service
Classifier: Intended Audience :: System Administrators
Classifier: License :: OSI Approved :: GNU General Public License v3 (GPLv3)
Classifier: Operating System :: Microsoft
Classifier: Operating System :: MacOS :: MacOS X
Classifier: Operating System :: Unix
Classifier: Operating System :: POSIX
Classifier: Programming Language :: Python
Classifier: Programming Language :: Python :: 3
Classifier: Programming Language :: Python :: 3.6
Classifier: Programming Language :: Python :: 3.7
Classifier: Programming Language :: Python :: 3.8
Classifier: Topic :: Software Development
Classifier: Topic :: Software Development :: Build Tools
Classifier: Topic :: Software Development :: Debuggers
Classifier: Topic :: Software Development :: Libraries
Classifier: Topic :: Software Development :: Libraries :: Python Modules
Classifier: Topic :: System :: Software Distribution
Classifier: Topic :: System :: Systems Administration
Classifier: Topic :: Utilities
Requires-Dist: just
Requires-Dist: pandas
Requires-Dist: metadate
Requires-Dist: tok
Requires-Dist: ijson
Requires-Dist: cython
Requires-Dist: pyarrow
Requires-Dist: tldextract
Requires-Dist: diskcache
Requires-Dist: requests-viewer
Requires-Dist: tzlocal
Requires-Dist: lxml
Requires-Dist: auto-extract (>=0.0.9)
Requires-Dist: google-api-python-client
Requires-Dist: python-dotenv
Requires-Dist: natura
Requires-Dist: selenium
Requires-Dist: psaw
Requires-Dist: icalevents
Requires-Dist: pytesseract
Requires-Dist: nostalgia-chrome
Requires-Dist: nostalgia-fitbit
